<Properties StartupConfiguration="{9E2AC577-7337-4E99-BB90-6C5301EE9921}|Default">
  <MonoDevelop.Ide.Workbench ActiveDocument="Views/Shared/_Layout.cshtml">
    <Files>
      <File FileName="Controllers/Account/AccountController.cs" Line="502" Column="1" />
      <File FileName="Models/DocumentType.cs" />
      <File FileName="Models/Enumeration.cs" />
      <File FileName="StaticDetails.cs" />
      <File FileName="Startup.cs" />
      <File FileName="Program.cs" Line="20" Column="13" />
      <File FileName="appsettings.json" />
      <File FileName="Controllers/Account/AccountOptions.cs" />
      <File FileName="Controllers/Account/ExternalController.cs" />
      <File FileName="Controllers/Account/RegisterViewModel.cs" Line="35" Column="1" />
      <File FileName="Controllers/Account/LogoutInputModel.cs" />
      <File FileName="Controllers/Account/LogoutViewModel.cs" />
      <File FileName="Controllers/Account/LoginInputModel.cs" />
      <File FileName="Controllers/Account/RedirectViewModel.cs" Line="1" Column="1" />
      <File FileName="Controllers/Account/LoginViewModel.cs" />
      <File FileName="Controllers/Account/LoggedOutViewModel.cs" />
      <File FileName="Controllers/Account/ExternalProvider.cs" />
      <File FileName="Models/ApplicationUser.cs" />
      <File FileName="Controllers/Document/DocumentRepository.cs" />
      <File FileName="Controllers/Document/ResponseDto.cs" />
      <File FileName="Controllers/Document/IDocumentRepository.cs" />
      <File FileName="Controllers/Document/DocumentDto.cs" />
      <File FileName="DbContexts/ApplicationDbContext.cs" Line="19" Column="1" />
      <File FileName="Models/ErrorViewModel.cs" />
      <File FileName="Views/Account/Register.cshtml" Line="50" Column="23" />
      <File FileName="Views/Account/Logout.cshtml" />
      <File FileName="Views/Account/Login.cshtml" />
      <File FileName="Views/Account/LoggedOut.cshtml" />
      <File FileName="Views/Account/AccessDenied.cshtml" />
      <File FileName="tempkey.jwk" />
      <File FileName="Migrations/20220522111238_IdentityTables2.cs" Line="1" Column="1" />
      <File FileName="Migrations/ApplicationDbContextModelSnapshot.cs" Line="1" Column="1" />
      <File FileName="Properties/launchSettings.json" Line="1" Column="1" />
      <File FileName="Views/Shared/_Layout.cshtml" Line="1" Column="1" />
    </Files>
    <Pads>
      <Pad Id="ProjectPad">
        <State name="__root__">
          <Node name="UserService" expanded="True">
            <Node name="UserService" expanded="True">
              <Node name="Dependencies" expanded="True" />
              <Node name="Controllers" expanded="True">
                <Node name="Account" expanded="True" />
                <Node name="Document" expanded="True" />
              </Node>
              <Node name="DbContexts" expanded="True" />
              <Node name="Migrations" expanded="True" />
              <Node name="Models" expanded="True" />
              <Node name="Properties" expanded="True" />
              <Node name="Views" expanded="True">
                <Node name="Account" expanded="True" />
                <Node name="Consent" expanded="True" />
                <Node name="Device" expanded="True" />
                <Node name="Diagnostics" expanded="True" />
                <Node name="Grants" expanded="True" />
                <Node name="Home" expanded="True" />
                <Node name="Shared" expanded="True">
                  <Node name="_Layout.cshtml" selected="True" />
                </Node>
              </Node>
            </Node>
          </Node>
        </State>
      </Pad>
    </Pads>
  </MonoDevelop.Ide.Workbench>
  <MonoDevelop.Ide.DebuggingService.PinnedWatches />
  <MonoDevelop.Ide.Workspace ActiveConfiguration="Debug" />
  <MonoDevelop.Ide.DebuggingService.Breakpoints>
    <BreakpointStore />
  </MonoDevelop.Ide.DebuggingService.Breakpoints>
  <MultiItemStartupConfigurations />
  <MonoDevelop.Ide.ItemProperties.UserService PreferredExecutionTarget="/Applications/Google Chrome.app" />
</Properties>